ai_rules_generator/__init__.py
ai_rules_generator/ai_general_guidelines.md
ai_rules_generator/ai_generator.py
ai_rules_generator/ai_rules_generator.py
ai_rules_generator/cli.py
ai_rules_generator/config.py
ai_rules_generator/config_manager.py
ai_rules_generator/detection.py
ai_rules_generator/file_utils.py
ai_rules_generator/generators.py
ai_rules_generator/generators_multi_tool.py
ai_rules_generator/generators_shared.py
ai_rules_generator/models.py
ai_rules_generator/awesome-cursorrules/LICENSE
ai_rules_generator/awesome-cursorrules/LOCKUP_VERTICAL_25D_DARK.png
ai_rules_generator/awesome-cursorrules/LOCKUP_VERTICAL_25D_LIGHT.png
ai_rules_generator/awesome-cursorrules/README.md
ai_rules_generator/awesome-cursorrules/Unblocked-logo-sq-words-over-gradient-1024w.png
ai_rules_generator/awesome-cursorrules/code-of-conduct.md
ai_rules_generator/awesome-cursorrules/contributing.md
ai_rules_generator/awesome-cursorrules/cursor-ai-logo.png
ai_rules_generator/awesome-cursorrules/rules/flutter-development-guidelines-cursorrules-prompt-file
ai_rules_generator/awesome-cursorrules/rules/android-jetpack-compose-cursorrules-prompt-file/android---project-structure.mdc
ai_rules_generator/awesome-cursorrules/rules/android-jetpack-compose-cursorrules-prompt-file/android-jetpack-compose---general-best-practices.mdc
ai_rules_generator/awesome-cursorrules/rules/android-jetpack-compose-cursorrules-prompt-file/android-jetpack-compose---performance-guidelines.mdc
ai_rules_generator/awesome-cursorrules/rules/android-jetpack-compose-cursorrules-prompt-file/android-jetpack-compose---testing-guidelines.mdc
ai_rules_generator/awesome-cursorrules/rules/android-jetpack-compose-cursorrules-prompt-file/android-jetpack-compose---ui-guidelines.mdc
ai_rules_generator/awesome-cursorrules/rules/angular-novo-elements-cursorrules-prompt-file/README.md
ai_rules_generator/awesome-cursorrules/rules/angular-novo-elements-cursorrules-prompt-file/angular-standalone-component-rules.mdc
ai_rules_generator-1.0.0.dist-info/licenses/LICENSE
ai_rules_generator-1.0.0.dist-info/METADATA
ai_rules_generator-1.0.0.dist-info/WHEEL
ai_rules_generator-1.0.0.dist-info/entry_points.txt
ai_rules_generator-1.0.0.dist-info/top_level.txt
ai_rules_generator-1.0.0.dist-info/RECORD
