Metadata-Version: 2.4
Name: ai-rules-generator
Version: 1.0.0
Summary: A CLI tool that generates comprehensive AI coding agent rules for Cursor and Claude Code
Author: AI Rules Generator Contributors
License-Expression: MIT
Project-URL: Homepage, https://github.com/rpupo63/ai-rules-generator
Project-URL: Documentation, https://github.com/rpupo63/ai-rules-generator#readme
Project-URL: Repository, https://github.com/rpupo63/ai-rules-generator
Project-URL: Issues, https://github.com/rpupo63/ai-rules-generator/issues
Keywords: cursor,claude,ai,rules,code-generation,coding-assistant
Classifier: Development Status :: 4 - Beta
Classifier: Intended Audience :: Developers
Classifier: Programming Language :: Python :: 3
Classifier: Programming Language :: Python :: 3.8
Classifier: Programming Language :: Python :: 3.9
Classifier: Programming Language :: Python :: 3.10
Classifier: Programming Language :: Python :: 3.11
Classifier: Programming Language :: Python :: 3.12
Classifier: Topic :: Software Development :: Libraries :: Python Modules
Classifier: Topic :: Software Development :: Code Generators
Requires-Python: >=3.8
License-File: LICENSE
Provides-Extra: openai
Requires-Dist: openai>=1.0.0; extra == "openai"
Provides-Extra: anthropic
Requires-Dist: anthropic>=0.18.0; extra == "anthropic"
Provides-Extra: all
Requires-Dist: openai>=1.0.0; extra == "all"
Requires-Dist: anthropic>=0.18.0; extra == "all"
Dynamic: license-file
Dynamic: requires-python
